test/__init__.py
test/test_text_game_maker/__init__.py
test/test_text_game_maker/test_game_objects/__init__.py
test/test_text_game_maker/test_game_objects/test_person.py
text_game_maker/__init__.py
text_game_maker/example.py
text_game_maker/runner.py
text_game_maker/slackbot_runner.py
text_game_maker/tgmdata_runner.py
text_game_maker/_old_example_map/__init__.py
text_game_maker/_old_example_map/example_map.py
text_game_maker/_old_example_map/example_map_rooms.py
text_game_maker/_old_example_map/hints.py
text_game_maker/_old_example_map/room_ids.py
text_game_maker/audio/__init__.py
text_game_maker/audio/audio.py
text_game_maker/builder/__init__.py
text_game_maker/builder/map_builder.py
text_game_maker/chatbot_utils/__init__.py
text_game_maker/chatbot_utils/redict.py
text_game_maker/chatbot_utils/responder.py
text_game_maker/crafting/__init__.py
text_game_maker/crafting/crafting.py
text_game_maker/event/__init__.py
text_game_maker/event/event.py
text_game_maker/example_map/__init__.py
text_game_maker/example_map/example_map.py
text_game_maker/example_map/example_map.tgmdata
text_game_maker/example_map/example_map_rooms.py
text_game_maker/example_map/hints.py
text_game_maker/example_map/room_ids.py
text_game_maker/game_objects/__init__.py
text_game_maker/game_objects/base.py
text_game_maker/game_objects/generic.py
text_game_maker/game_objects/items.py
text_game_maker/game_objects/living.py
text_game_maker/game_objects/person.py
text_game_maker/materials/__init__.py
text_game_maker/materials/materials.py
text_game_maker/messages/__init__.py
text_game_maker/messages/messages.py
text_game_maker/parser/__init__.py
text_game_maker/parser/commands.py
text_game_maker/parser/parser.py
text_game_maker/player/__init__.py
text_game_maker/player/player.py
text_game_maker/ptttl/__init__.py
text_game_maker/ptttl/ptttl_audio_encoder.py
text_game_maker/ptttl/ptttl_parser.py
text_game_maker/ptttl-data/allstar_bach_chorale.txt
text_game_maker-0.7.5.dist-info/DESCRIPTION.rst
text_game_maker-0.7.5.dist-info/METADATA
text_game_maker-0.7.5.dist-info/RECORD
text_game_maker-0.7.5.dist-info/WHEEL
text_game_maker-0.7.5.dist-info/metadata.json
text_game_maker-0.7.5.dist-info/top_level.txt
