Metadata-Version: 2.0
Name: text-game-maker
Version: 0.7.5
Summary: Framework for making text-based adventure games (interactive finction)
Home-page: http://github.com/eriknyquist/text_game_maker
Author: Erik Nyquist
Author-email: eknyquist@gmail.com
License: Apache 2.0
Platform: UNKNOWN
Requires-Dist: future
Requires-Dist: prompt-toolkit
Requires-Dist: pygame
Requires-Dist: tones
